generate_random_values_in_range/LICENSE
generate_random_values_in_range/README.MD
generate_random_values_in_range/__init__.py
generate_random_values_in_range/requirements.txt
generate_random_values_in_range/thirdparty.json
generate_random_values_in_range-0.10.dist-info/LICENSE.rst
generate_random_values_in_range-0.10.dist-info/METADATA
generate_random_values_in_range-0.10.dist-info/WHEEL
generate_random_values_in_range-0.10.dist-info/top_level.txt
generate_random_values_in_range-0.10.dist-info/RECORD
